transfer/__init__.py
transfer/__main__.py
transfer/augment_arrays.py
transfer/grad_cam.py
transfer/images_to_array.py
transfer/inception_v3.py
transfer/input.py
transfer/model.py
transfer/pre_model.py
transfer/predict_model.py
transfer/project.py
transfer/resnet50.py
transfer/server.py
transfer/split.py
transfer/vgg16.py
transfer/xception.py
transfer-0.40.dist-info/DESCRIPTION.rst
transfer-0.40.dist-info/METADATA
transfer-0.40.dist-info/RECORD
transfer-0.40.dist-info/WHEEL
transfer-0.40.dist-info/entry_points.txt
transfer-0.40.dist-info/metadata.json
transfer-0.40.dist-info/top_level.txt
