Metadata-Version: 2.0
Name: transfer
Version: 0.40
Summary: Transfer learning for deep image classification
Home-page: http://github.com/matthew-sochor/transfer
Author: Matthew Sochor
Author-email: matthew.sochor@gmail.com
License: MIT
Download-URL: http://github.com/matthew-sochor/transfer
Keywords: keras transfer learning resnet deep neural net image classification command line
Platform: UNKNOWN
Requires-Python: >=3
Requires-Dist: numpy
Requires-Dist: keras
Requires-Dist: pyyaml
Requires-Dist: tqdm
Requires-Dist: pandas
Requires-Dist: opencv-python
Requires-Dist: termcolor
Requires-Dist: colorama
Requires-Dist: flask
Requires-Dist: flask-jsonpify
Requires-Dist: flask-restful
Requires-Dist: matplotlib
Requires-Dist: pillow
Requires-Dist: h5py
Requires-Dist: scikit-learn
Requires-Dist: seaborn
